cvlab/__init__.py
cvlab/common/__init__.py
cvlab/common/detection.py
cvlab/common/factory.py
cvlab/common/utils.py
cvlab/common/visualization.py
cvlab/common/libs/__init__.py
cvlab/common/libs/box.py
cvlab/common/libs/pretty_confmat.py
cvlab/converter/__init__.py
cvlab/converter/onnx2tf.py
cvlab/converter/torch2onnx.py
cvlab/datasets/__init__.py
cvlab/datasets/base.py
cvlab/datasets/transform.py
cvlab/datasets/detection/__init__.py
cvlab/datasets/detection/coco.py
cvlab/datasets/detection/generic_detection.py
cvlab/datasets/detection/labelme.py
cvlab/datasets/detection/yolo.py
cvlab/datasets/segmentation/__init__.py
cvlab/datasets/segmentation/apolloscape_laneseg.py
cvlab/datasets/segmentation/generic_segmentation.py
cvlab/engine/__init__.py
cvlab/engine/detection_evaluator.py
cvlab/engine/predictor.py
cvlab/engine/trainer.py
cvlab/loss/__init__.py
cvlab/loss/dice.py
cvlab/loss/focal.py
cvlab/metrics/__init__.py
cvlab/metrics/classification.py
cvlab/metrics/detection.py
cvlab/models/__init__.py
cvlab/models/base.py
cvlab/models/deeplab/__init__.py
cvlab/models/deeplab/deeplab.py
cvlab/models/deeplab/mobilenetv2.py
cvlab/models/deeplab/modeling.py
cvlab/models/deeplab/resnet.py
cvlab/models/deeplab/utils.py
cvlab/structures/__init__.py
cvlab/structures/common.py
cvlab/structures/instance2d.py
cvlab_dl-0.0.1.dist-info/LICENSE
cvlab_dl-0.0.1.dist-info/METADATA
cvlab_dl-0.0.1.dist-info/WHEEL
cvlab_dl-0.0.1.dist-info/top_level.txt
cvlab_dl-0.0.1.dist-info/RECORD
