Metadata-Version: 2.1
Name: cvlab-dl
Version: 0.0.1
Summary: An unified laboratory/framework for Computer Vision research, development and deployment.
Home-page: https://github.com/AlanDecode/cvlab
Author: AlanDecode
Author-email: zytbuaa1415@gmail.com
License: MIT
Platform: UNKNOWN
Classifier: License :: OSI Approved :: MIT License
Classifier: Programming Language :: Python
Classifier: Programming Language :: Python :: 3
Classifier: Programming Language :: Python :: 3.6
Classifier: Programming Language :: Python :: Implementation :: CPython
Classifier: Programming Language :: Python :: Implementation :: PyPy
Requires-Python: >=3.6.0
Requires-Dist: torch (>=1.6.0)
Requires-Dist: torchvision (>=1.7.0)
Requires-Dist: tensorflow (<2)
Requires-Dist: flake8
Requires-Dist: yapf
Requires-Dist: sklearn
Requires-Dist: scipy
Requires-Dist: shapely
Requires-Dist: matplotlib
Requires-Dist: seaborn
Requires-Dist: pandas
Requires-Dist: pyyaml
Requires-Dist: opencv-python
Requires-Dist: opencv-contrib-python
Requires-Dist: onnx
Requires-Dist: onnxruntime
Requires-Dist: onnx-simplifier
Requires-Dist: tqdm
Requires-Dist: prettytable
